COPYING
LICENSE
MANIFEST.in
README.md
requirements-test.txt
requirements.txt
setup.py
django_tastypie_elasticsearch.egg-info/PKG-INFO
django_tastypie_elasticsearch.egg-info/SOURCES.txt
django_tastypie_elasticsearch.egg-info/dependency_links.txt
django_tastypie_elasticsearch.egg-info/requires.txt
django_tastypie_elasticsearch.egg-info/top_level.txt
django_tastypie_elasticsearch.egg-info/zip-safe
docs/Makefile
docs/conf.py
docs/index.rst
docs/installation.rst
docs/make.bat
docs/resources.rst
docs/usage.rst
tastypie_elasticsearch/__init__.py
tastypie_elasticsearch/paginator.py
tastypie_elasticsearch/resources.py