Metadata-Version: 1.1
Name: django-tastypie-elasticsearch
Version: 0.5.0
Summary: ElasticSearch Resource for django-tastypie.
Home-page: https://github.com/llonchj/django-tastypie-elasticsearch
Author: Jordi Llonch
Author-email: llonchj@gmail.com
License: AGPLv3
Keywords: REST RESTful tastypie elasticsearch django
Platform: UNKNOWN
Classifier: Development Status :: 4 - Beta
Classifier: Environment :: Web Environment
Classifier: Intended Audience :: Developers
Classifier: License :: OSI Approved :: GNU Affero General Public License v3
Classifier: Operating System :: OS Independent
Classifier: Programming Language :: Python
Classifier: Framework :: Django
